gdistance-1.0.4.data/purelib/gdistance/__init__.py
gdistance-1.0.4.data/purelib/gdistance/_core.cp37-win32.pyd
gdistance-1.0.4.data/purelib/gdistance/_core.py
gdistance-1.0.4.data/purelib/gdistance/core.py
gdistance-1.0.4.data/purelib/gdistance/gdal_calc.py
gdistance-1.0.4.data/purelib/gdistance/gdal_merge.py
gdistance-1.0.4.data/purelib/gdistance/gdal_reclassify.py
gdistance-1.0.4.data/purelib/gdistance/gdistance.py
gdistance-1.0.4.data/purelib/gdistance/raster.py
gdistance-1.0.4.data/purelib/gdistance/utils.py
gdistance-1.0.4.dist-info/METADATA
gdistance-1.0.4.dist-info/WHEEL
gdistance-1.0.4.dist-info/top_level.txt
gdistance-1.0.4.dist-info/RECORD
