Metadata-Version: 2.1
Name: gdistance
Version: 1.0.4
Summary: Python package for the gdistance
Home-page: https://github.com/robertohuru/gdistance
Author: Robert Ohuru
Author-email: robertohuru@gmail.com
License: UNKNOWN
Platform: UNKNOWN
Classifier: Development Status :: 5 - Production/Stable
Classifier: Intended Audience :: Developers
Classifier: License :: OSI Approved :: Apache Software License
Classifier: Operating System :: OS Independent
Classifier: Programming Language :: Python
Classifier: Topic :: Software Development :: Libraries :: Python Modules
Requires-Python: >=3.6
